README.rst
setup.py
mtvc_api_client.egg-info/PKG-INFO
mtvc_api_client.egg-info/SOURCES.txt
mtvc_api_client.egg-info/dependency_links.txt
mtvc_api_client.egg-info/not-zip-safe
mtvc_api_client.egg-info/pbr.json
mtvc_api_client.egg-info/requires.txt
mtvc_api_client.egg-info/top_level.txt
mtvc_client/__init__.py
mtvc_client/client.py
mtvc_client/libs/__init__.py
mtvc_client/libs/django/__init__.py
mtvc_client/libs/django/decorators.py
mtvc_client/libs/django/forms.py
mtvc_client/libs/django/middleware.py
mtvc_client/libs/django/urls.py
mtvc_client/libs/django/utils.py
mtvc_client/libs/django/views.py
mtvc_client/tests/__init__.py
mtvc_client/tests/test_client.py