Metadata-Version: 1.1
Name: mtvc-api-client
Version: 0.0.12
Summary: Praekelt MTVC API Client
Home-page: https://github.com/praekelt/mtvc-api-client
Author: Praekelt Consulting
Author-email: dev@praekelt.com
License: UNKNOWN
Platform: UNKNOWN
Classifier: Development Status :: 5 - Production/Stable
Classifier: Intended Audience :: Developers
Classifier: License :: OSI Approved :: BSD License
Classifier: Operating System :: POSIX
Classifier: Programming Language :: Python
Classifier: Topic :: Software Development :: Libraries :: Python Modules
Classifier: Topic :: System :: Networking
